pagefind/__init__.py
pagefind/__main__.py
pagefind/index/__init__.py
pagefind/py.typed
pagefind/service/__init__.py
pagefind/service/types.py
pagefind-1.4.0.dist-info/METADATA
pagefind-1.4.0.dist-info/WHEEL
pagefind-1.4.0.dist-info/RECORD
