Metadata-Version: 2.3
Name: pagefind
Version: 1.4.0
Summary: Python API for Pagefind
License: MIT
Author: Pagefind
Requires-Python: >=3.9
Classifier: License :: OSI Approved :: MIT License
Classifier: Programming Language :: Python :: 3
Classifier: Programming Language :: Python :: 3.9
Classifier: Programming Language :: Python :: 3.10
Classifier: Programming Language :: Python :: 3.11
Classifier: Programming Language :: Python :: 3.12
Classifier: Programming Language :: Python :: 3.13
Classifier: Topic :: Text Processing :: Indexing
Classifier: Topic :: Text Processing :: Markup :: HTML
Provides-Extra: bin
Provides-Extra: extended
Requires-Dist: pagefind_bin (>=1.4.0,<1.5.0) ; extra == "bin"
Requires-Dist: pagefind_bin_extended (>=1.4.0,<1.5.0) ; extra == "extended"
